Taint_Tracking/MultiplierControl_TaintTrack.v
//==============================================================================
// Control Module for Sequential Multiplier with Taint Tracking
//==============================================================================

module MultiplierControl_TaintTrack #(parameter WIDTH = 4)(
	// External Inputs
	input   clk,           // Clock
    input   rst,           // reset
	input   start,
    input   start_t,

    // External Output
    output reg productDone,
    output reg productDone_t,

	// Outputs to Datapath
	output reg  rsload,
    output reg  rsload_t,
	output reg  rsclear,
    output reg  rsclear_t,
	output reg  rsshr,
    output reg  rsshr_t,
    output reg  mrld,
    output reg  mrld_t,
    output reg  mdld,
    output reg  mdld_t,

	// Inputs from Datapath
    input [WIDTH - 1:0] multiplierReg,
    input [WIDTH - 1:0] multiplierReg_t
);
	// Local Vars
	// # of states = 2 * WIDTH + 3
    localparam STATE_WIDTH = $clog2(2 * WIDTH + 3);
    reg [STATE_WIDTH - 1:0] state;
    reg [STATE_WIDTH - 1:0] state_t;
	reg [STATE_WIDTH - 1:0] next_state;
	reg [STATE_WIDTH - 1:0] next_state_t;

	localparam START = 4'd0;
	localparam INIT = 4'd1;
    localparam FINAL = 2 * (WIDTH + 1);
    // BIT_n = 2*n, BIT_n_TRUE = 2*n + 1, FINAL = 2*(N+1)

	// Output Combinational Logic
	always @( * ) begin
		// Set defaults
        rsload = 0;
        rsclear = 0;
        rsshr = 0;
        mrld = 0;
        mdld = 0;
        productDone = 0;
        if (state == START) begin
        end
        else if (state == INIT) begin
            mdld = 1;
            mrld = 1;
            rsclear = 1;

            mdld_t = mdld_t || state_t;
            mrld_t = mrld_t || state_t;
            rsclear_t = rsclear_t || state_t;
        end
        else if (state == FINAL) begin
            rsshr = 1;
            productDone = 1;

            rsshr_t = rsshr_t || state_t;
            productDone_t = productDone_t || state_t;
        end
        else if (state[0] == 1) begin
            rsload = 1;

            rsload_t = rsload_t || state_t;
        end
        else begin
            rsshr = 1;

            rsshr_t = rsshr_t || state_t;
        end
	end

	// Next State Combinational Logic
	always @( * ) begin
		next_state = state;
        next_state_t = state_t;
		
		if (state == START) begin
			if (start) begin
				next_state = INIT;
			end
            next_state_t = next_state_t || start_t;
		end
		else if (state == INIT) begin
			next_state = 2;
		end
        else if (state == FINAL) begin
            next_state = START;
        end
        else if (state[0] == 0) begin
            if (multiplierReg[(state >> 1) - 1]) begin
                next_state = next_state + 1;
            end
            else begin
                next_state = next_state + 2;
            end
            next_state_t = next_state_t || multiplierReg_t[(state >> 1) - 1];
        end
        else begin
            next_state = next_state + 1;
        end
	end

	// State Update Sequential Logic
	always @(posedge clk) begin
		if (rst) begin
			state <= START;
		end
		else begin
			// Update state to next state
			state <= next_state;
            state_t <= next_state_t;
		end
	end

endmodule

Taint_Tracking/MultiplierDatapath_TaintTrack.v
//==============================================================================
// Datapath Module for Sequential Multiplier
//==============================================================================

module MultiplierDatapath_TaintTrack #(parameter WIDTH = 1024)(

    // External Inputs
    input   clk,       // Clock 
    input wire [WIDTH - 1:0] multiplier,
    input wire [WIDTH - 1:0] multiplier_t,
    input wire [WIDTH - 1:0] multiplicand,
    input wire [WIDTH - 1:0] multiplicand_t,

    // External Output
    output wire [WIDTH*2 - 1:0] product,
    output wire [WIDTH*2 - 1:0] product_t,

    // Inputs from Controller
    input rsload,
    input rsload_t,
    input rsclear,
    input rsclear_t,
    input rsshr,
    input rsshr_t,
    input mrld,
    input mrld_t,
    input mdld,
    input mdld_t,

    // Outputs to Controller
    output reg [WIDTH - 1:0] multiplierReg,
    output reg [WIDTH - 1:0] multiplierReg_t,

    // debug outputs
    output reg [WIDTH*2:0] runningSumReg,
    output reg [WIDTH*2:0] runningSumReg_t,
    output reg [WIDTH*2:0] multiplicandReg,
    output reg [WIDTH*2:0] multiplicandReg_t
);

reg [WIDTH*2:0] carryIn;
reg [WIDTH*2:0] carryIn_t;
integer i;

// Sequential Logic
always @( posedge clk) begin
    
    // init registers
    if (mdld) begin
        multiplicandReg <= multiplicand << WIDTH;
        multiplicandReg_t <= multiplicand_t << WIDTH | {WIDTH{mdld_t}};
    end
    else begin
        multiplicandReg_t <= multiplicandReg_t | {WIDTH{mdld_t}};
    end

    if (mrld) begin
        multiplierReg <= multiplier;
        multiplierReg_t <= multiplier_t | {WIDTH{mrld_t}};
    end
    else begin
        multiplierReg_t <= multiplierReg_t | {WIDTH{mrld_t}};
    end

    if (rsclear) begin
        runningSumReg <= 0;
        runningSumReg_t <= 0 | {WIDTH{rsclear_t}} | {WIDTH{rsload_t}} | {WIDTH{rsshr_t}};
    end

    // load running sum
    else if (rsload) begin
        runningSumReg <= multiplicandReg + runningSumReg; 

        // carry taint logic
        carryIn[0] = 0;
        carryIn_t[0] = 0;
        for (i = 0; i < 2 * WIDTH - 1; i = i + 1) begin

            // check if there is a carry-out from i
            if (((multiplicandReg[i] & runningSumReg[i]) | 
                 (multiplicandReg[i] & carryIn[i]) |
                  (runningSumReg[i] & carryIn[i]))) 
            begin
                  carryIn[i + 1] = 1;

                  // check if the carry-out from i should be tainted
                  if (multiplicandReg_t[i] | runningSumReg_t[i]) begin
                    carryIn_t[i + 1] = 1;
                  end
                  else begin
                    carryIn_t[i + 1] = 0;
                  end
            end
            else begin
                carryIn[i + 1] = 0;
                carryIn_t[i + 1] = 0;
            end
        end
        runningSumReg_t <= carryIn_t | runningSumReg_t | multiplicandReg_t | {WIDTH{rsclear_t}} | {WIDTH{rsload_t}} | {WIDTH{rsshr_t}};
    end

    else if (rsshr) begin
        runningSumReg <= runningSumReg >>> 1; 
        runningSumReg_t <= runningSumReg_t | {WIDTH{rsclear_t}} | {WIDTH{rsload_t}} | {WIDTH{rsshr_t}};
    end

    else begin 
        runningSumReg_t <= runningSumReg_t | {WIDTH{rsclear_t}} | {WIDTH{rsload_t}} | {WIDTH{rsshr_t}};
    end

    end 
    assign product = runningSumReg;
    assign product_t = runningSumReg_t;
endmodule

Taint_Tracking/Multiplier_TaintTrack.v
//==============================================================================
// Multiplier Module with Taint Tracking
//==============================================================================

`include "MultiplierControl_TaintTrack.v"
`include "MultiplierDatapath_TaintTrack.v"

module Multiplier_TaintTrack #(parameter WIDTH = 4)(
	input   clk,
	input   rst,
    input   start,
    input   start_t,
    input [WIDTH - 1:0] multiplier,
    input [WIDTH - 1:0] multiplier_t,
    input [WIDTH - 1:0] multiplicand,
    input [WIDTH - 1:0] multiplicand_t,

	output [2*WIDTH - 1:0] product,
    output [2*WIDTH - 1:0] product_t,
    output productDone,
    output productDone_t
);
	// Declare local connections here
	wire rsload;
    wire rsload_t;
	wire rsclear;
    wire rsclear_t;
	wire rsshr;
    wire rsshr_t;
	wire mrld;
    wire mrld_t;
	wire mdld;
    wire mdld_t;
    wire [WIDTH - 1:0] multiplierReg;
    wire [WIDTH - 1:0] multiplierReg_t;
    wire [WIDTH * 2:0] runningSumReg;
    wire [WIDTH * 2:0] runningSumReg_t;
    wire [WIDTH * 2:0] multiplicandReg;
    wire [WIDTH * 2:0] multiplicandReg_t;

	// Datapath -- check port connections/rename
	MultiplierDatapath_TaintTrack #(WIDTH) dpath(
		.clk    (clk),
        .multiplier (multiplier),
        .multiplier_t (multiplier_t),
        .multiplicand (multiplicand),
        .multiplicand_t (multiplicand_t),
        .rsload (rsload),
        .rsload_t (rsload_t),
        .rsclear (rsclear),
        .rsclear_t (rsclear_t),
        .rsshr (rsshr),
        .rsshr_t (rsshr_t),
        .mrld (mrld),
        .mrld_t (mrld_t),
        .mdld (mdld),
        .mdld_t (mdld_t),
        .product (product),
        .product_t (product_t),
        .multiplierReg (multiplierReg),
        .multiplierReg_t (multiplierReg_t),
        .runningSumReg (runningSumReg),
        .runningSumReg_t (runningSumReg_t),
        .multiplicandReg (multiplicandReg),
        .multiplicandReg_t (multiplicandReg_t)
	);

	// Control
	MultiplierControl_TaintTrack #(WIDTH) ctrl(
		.clk  (clk),
		.rst  (rst),
        .start (start),
        .start_t (start_t),
        .rsload (rsload),
        .rsload_t (rsload_t),
        .rsclear (rsclear),
        .rsclear_t (rsclear_t),
        .rsshr (rsshr),
        .rsshr_t (rsshr_t),
        .mrld (mrld),
        .mrld_t (mrld_t),
        .mdld (mdld),
        .mdld_t (mdld_t),
        .multiplierReg (multiplierReg),
        .multiplierReg_t (multiplierReg_t),
        .productDone (productDone),
        .productDone_t (productDone_t)
	);

endmodule

Taint_Tracking/Multiplier_TaintTrack.t.v
//===============================================================================
// Testbench Module for Multiplier
// some code adapted from ECE206 testing material
//===============================================================================
`timescale 1ns/100ps

`include "Multiplier_TaintTrack.v"

`define ASSERT_EQ(ONE, TWO, MSG)               \
	begin                                      \
		if ((ONE) !== (TWO)) begin             \
			$display("\t[FAILURE]:%s", (MSG)); \
			errors = errors + 1;               \
		end                                    \
	end #0

`define SET(VAR, VALUE) $display("Setting %s to %s...", "VAR", "VALUE"); #1; VAR = (VALUE); #1

`define CLOCK $display("Pressing uclk..."); #1; clk = 1; #1; clk = 0; #1

`define SHOW_STATE(STATE) $display("\nEntering State: %s\n-----------------------------------", STATE)

module MultiplierTest;
    parameter NUM_BITS = 7;

	// Local Vars
	reg clk = 0;
	reg rst = 0;
	reg start = 0;
	reg [NUM_BITS - 1:0] multiplier = 7'd0;
	reg [NUM_BITS - 1:0] multiplicand = 7'd0;
    reg start_t = 0;
	reg [NUM_BITS - 1:0] multiplier_t = 7'd0;
	reg [NUM_BITS - 1:0] multiplicand_t = 7'd0;
    wire [2 * NUM_BITS - 1:0] product;

	// Error Counts
	reg [7:0] errors = 0;

	// VCD Dump
	initial begin
		$dumpfile("MultiplierTest.vcd");
		$dumpvars;
	end

	// Multiplier Module
	Multiplier_TaintTrack #(NUM_BITS) multipliertester(
        .clk    (clk),
		.rst    (rst),
        .start  (start),
        .multiplier (multiplier),
        .multiplicand (multiplicand),
        .product (product),
        .start_t (start_t),
        .multiplier_t (multiplier_t),
        .multiplicand_t (multiplicand_t)
	);

    integer i;
	// Main Test Logic
	initial begin
        // 0110 x 0011
        /*
        `SET(multiplier, 4'b0011)
        `SET(multiplicand, 4'b0110)

		// Reset the multiplier
		`SET(rst, 1);
		`CLOCK;

		// START State
		`SET(rst, 0);
        `SET(start, 1);
        `CLOCK;

        // INIT State - should take at most 10 clock cycles to get back to START
        `SET(start, 0);
        for (i = 0; i < 10; i = i + 1) begin
            `CLOCK;
        end
        `ASSERT_EQ(product, 8'b00010010, "Product is incorrect");
        */

        // 15 x 15
        `SET(multiplier, 15)
        `SET(multiplicand, 15)

		`SET(rst, 1);
		`CLOCK;

		`SET(rst, 0);
        `SET(start, 1);
        `CLOCK;

        `SET(start, 0);

        for (i = 0; i < 100; i = i + 1) begin
            `CLOCK;
        end
        `ASSERT_EQ(product, 225, "Product is incorrect");
        $display("%b", product);

        // 0 x 12
        `SET(multiplier, 0)
        `SET(multiplicand, 12)

		`SET(rst, 1);
		`CLOCK;

		`SET(rst, 0);
        `SET(start, 1);
        `CLOCK;

        `SET(start, 0);

        for (i = 0; i < 10; i = i + 1) begin
            `CLOCK;
        end
        `ASSERT_EQ(product, 0, "Product is incorrect");

        // 1 x 2
        `SET(multiplier, 1)
        `SET(multiplicand, 2)

		`SET(rst, 1);
		`CLOCK;

		`SET(rst, 0);
        `SET(start, 1);
        `CLOCK;

        `SET(start, 0);

        for (i = 0; i < 100; i = i + 1) begin
            `CLOCK;
        end
        `ASSERT_EQ(product, 2, "Product is incorrect");

        // 0 x 0 
        `SET(multiplier, 0)
        `SET(multiplicand, 0)

		`SET(rst, 1);
		`CLOCK;

		`SET(rst, 0);
        `SET(start, 1);
        `CLOCK;

        `SET(start, 0);

        for (i = 0; i < 100; i = i + 1) begin
            `CLOCK;
        end
        `ASSERT_EQ(product, 0, "Product is incorrect");

        // 92 * 75
        `SET(multiplier, 92)
        `SET(multiplicand, 75)

		`SET(rst, 1);
		`CLOCK;

		`SET(rst, 0);
        `SET(start, 1);
        `CLOCK;

        `SET(start, 0);

        for (i = 0; i < 100; i = i + 1) begin
            `CLOCK;
        end
        `ASSERT_EQ(product, 6900, "Product is incorrect");

        // 42 * 78
        `SET(multiplier, 42)
        `SET(multiplicand, 78)

		`SET(rst, 1);
		`CLOCK;

		`SET(rst, 0);
        `SET(start, 1);
        `CLOCK;

        `SET(start, 0);

        for (i = 0; i < 100; i = i + 1) begin
            `CLOCK;
        end
        `ASSERT_EQ(product, 3276, "Product is incorrect");


		$display("\nTESTS COMPLETED (%d FAILURES)", errors);
		$finish;
	end

endmodule

Taint_Tracking/MultiplierTest.vcd
$date
	Mon Jun 24 13:49:36 2024
$end
$version
	Icarus Verilog
$end
$timescale
	100ps
$end
$scope module MultiplierTest $end
$var wire 14 ! product [13:0] $end
$var parameter 32 " NUM_BITS $end
$var reg 1 # clk $end
$var reg 8 $ errors [7:0] $end
$var reg 7 % multiplicand [6:0] $end
$var reg 7 & multiplicand_t [6:0] $end
$var reg 7 ' multiplier [6:0] $end
$var reg 7 ( multiplier_t [6:0] $end
$var reg 1 ) rst $end
$var reg 1 * start $end
$var reg 1 + start_t $end
$var integer 32 , i [31:0] $end
$scope module multipliertester $end
$var wire 1 # clk $end
$var wire 7 - multiplicand [6:0] $end
$var wire 7 . multiplicand_t [6:0] $end
$var wire 7 / multiplier [6:0] $end
$var wire 7 0 multiplier_t [6:0] $end
$var wire 1 ) rst $end
$var wire 1 * start $end
$var wire 1 + start_t $end
$var wire 15 1 runningSumReg_t [14:0] $end
$var wire 15 2 runningSumReg [14:0] $end
$var wire 1 3 rsshr_t $end
$var wire 1 4 rsshr $end
$var wire 1 5 rsload_t $end
$var wire 1 6 rsload $end
$var wire 1 7 rsclear_t $end
$var wire 1 8 rsclear $end
$var wire 14 9 product_t [13:0] $end
$var wire 1 : productDone_t $end
$var wire 1 ; productDone $end
$var wire 14 < product [13:0] $end
$var wire 7 = multiplierReg_t [6:0] $end
$var wire 7 > multiplierReg [6:0] $end
$var wire 15 ? multiplicandReg_t [14:0] $end
$var wire 15 @ multiplicandReg [14:0] $end
$var wire 1 A mrld_t $end
$var wire 1 B mrld $end
$var wire 1 C mdld_t $end
$var wire 1 D mdld $end
$var parameter 32 E WIDTH $end
$scope module ctrl $end
$var wire 1 # clk $end
$var wire 1 ) rst $end
$var wire 1 * start $end
$var wire 1 + start_t $end
$var wire 7 F multiplierReg_t [6:0] $end
$var wire 7 G multiplierReg [6:0] $end
$var parameter 65 H FINAL $end
$var parameter 4 I INIT $end
$var parameter 4 J START $end
$var parameter 32 K STATE_WIDTH $end
$var parameter 32 L WIDTH $end
$var reg 1 D mdld $end
$var reg 1 C mdld_t $end
$var reg 1 B mrld $end
$var reg 1 A mrld_t $end
$var reg 5 M next_state [4:0] $end
$var reg 5 N next_state_t [4:0] $end
$var reg 1 ; productDone $end
$var reg 1 : productDone_t $end
$var reg 1 8 rsclear $end
$var reg 1 7 rsclear_t $end
$var reg 1 6 rsload $end
$var reg 1 5 rsload_t $end
$var reg 1 4 rsshr $end
$var reg 1 3 rsshr_t $end
$var reg 5 O state [4:0] $end
$var reg 5 P state_t [4:0] $end
$upscope $end
$scope module dpath $end
$var wire 1 # clk $end
$var wire 1 D mdld $end
$var wire 1 C mdld_t $end
$var wire 1 B mrld $end
$var wire 1 A mrld_t $end
$var wire 7 Q multiplicand [6:0] $end
$var wire 7 R multiplicand_t [6:0] $end
$var wire 7 S multiplier [6:0] $end
$var wire 7 T multiplier_t [6:0] $end
$var wire 1 8 rsclear $end
$var wire 1 7 rsclear_t $end
$var wire 1 6 rsload $end
$var wire 1 5 rsload_t $end
$var wire 1 4 rsshr $end
$var wire 1 3 rsshr_t $end
$var wire 14 U product_t [13:0] $end
$var wire 14 V product [13:0] $end
$var parameter 32 W WIDTH $end
$var reg 15 X carryIn [14:0] $end
$var reg 15 Y carryIn_t [14:0] $end
$var reg 15 Z multiplicandReg [14:0] $end
$var reg 15 [ multiplicandReg_t [14:0] $end
$var reg 7 \ multiplierReg [6:0] $end
$var reg 7 ] multiplierReg_t [6:0] $end
$var reg 15 ^ runningSumReg [14:0] $end
$var reg 15 _ runningSumReg_t [14:0] $end
$var integer 32 ` i [31:0] $end
$upscope $end
$upscope $end
$upscope $end
$enddefinitions $end
$comment Show the parameter values. $end
$dumpall
b111 W
b111 L
b101 K
b0 J
b1 I
b10000 H
b111 E
b111 "
$end
#0
$dumpvars
bx `
bx _
bx ^
bx ]
bx \
bx [
bx Z
bx Y
bx X
bx V
bx U
b0 T
b0 S
b0 R
b0 Q
bx P
bx O
bx N
bx M
bx G
bx F
xD
xC
xB
xA
bx @
bx ?
bx >
bx =
bx <
x;
x:
bx 9
x8
x7
x6
x5
x4
x3
bx 2
bx 1
b0 0
b0 /
b0 .
b0 -
bx ,
0+
0*
0)
b0 (
b0 '
b0 &
b0 %
b0 $
0#
bx !
$end
#10
b1111 '
b1111 /
b1111 S
#30
b1111 %
b1111 -
b1111 Q
#50
1)
#70
b0 M
0;
0C
0D
0A
0B
03
04
07
08
05
06
b0 O
1#
#80
0#
#100
0)
#120
b1 M
1*
#140
b10 M
x7
xA
xC
18
1B
1D
b1 O
1#
#150
0#
#170
b10 M
0*
#180
b0 ,
#190
b0xxxxxxx 9
b0xxxxxxx U
b0 !
b0 <
b0 V
b11 M
x3
14
0C
0D
0A
0B
07
08
b0xxxxxxx 1
b0xxxxxxx _
b0 2
b0 ^
b1111 >
b1111 G
b1111 \
b0xxxxxxx ?
b0xxxxxxx [
b11110000000 @
b11110000000 Z
b10 O
1#
#200
0#
#210
b1 ,
#220
b100 M
x5
16
03
04
b11 O
1#
#230
0#
#240
b10 ,
#250
b11110000000 !
b11110000000 <
b11110000000 V
b101 M
x3
14
05
06
b11110000000 2
b11110000000 ^
b100 O
b1110 `
b0 Y
b0 X
1#
#260
0#
#270
b11 ,
#280
b110 M
x5
16
03
04
b1111000000 !
b1111000000 <
b1111000000 V
b101 O
b1111000000 2
b1111000000 ^
1#
#290
0#
#300
b100 ,
#310
b101101000000 !
b101101000000 <
b101101000000 V
b111 M
x3
14
05
06
b101101000000 2
b101101000000 ^
b110 O
b111100000000 X
b1110 `
1#
#320
0#
#330
b101 ,
#340
b1000 M
x5
16
03
04
b10110100000 !
b10110100000 <
b10110100000 V
b111 O
b10110100000 2
b10110100000 ^
1#
#350
0#
#360
b110 ,
#370
b110100100000 !
b110100100000 <
b110100100000 V
b1001 M
x3
14
05
06
b110100100000 2
b110100100000 ^
b1000 O
b1110 `
1#
#380
0#
#390
b111 ,
#400
b1010 M
x5
16
03
04
b11010010000 !
b11010010000 <
b11010010000 V
b1001 O
b11010010000 2
b11010010000 ^
1#
#410
0#
#420
b1000 ,
#430
b111000010000 !
b111000010000 <
b111000010000 V
b1100 M
x3
14
05
06
b111000010000 2
b111000010000 ^
b1010 O
b1110 `
1#
#440
0#
#450
b1001 ,
#460
b1110 M
x3
14
b11100001000 !
b11100001000 <
b11100001000 V
b1100 O
b11100001000 2
b11100001000 ^
1#
#470
0#
#480
b1010 ,
#490
b1110000100 !
b1110000100 <
b1110000100 V
b10000 M
x3
14
b1110000100 2
b1110000100 ^
b1110 O
1#
#500
0#
#510
b1011 ,
#520
b0 M
1;
x3
14
b111000010 !
b111000010 <
b111000010 V
b10000 O
b111000010 2
b111000010 ^
1#
#530
0#
#540
b1100 ,
#550
b11100001 !
b11100001 <
b11100001 V
0;
03
04
b11100001 2
b11100001 ^
b0 O
1#
#560
0#
#570
b1101 ,
#580
1#
#590
0#
#600
b1110 ,
#610
1#
#620
0#
#630
b1111 ,
#640
1#
#650
0#
#660
b10000 ,
#670
1#
#680
0#
#690
b10001 ,
#700
1#
#710
0#
#720
b10010 ,
#730
1#
#740
0#
#750
b10011 ,
#760
1#
#770
0#
#780
b10100 ,
#790
1#
#800
0#
#810
b10101 ,
#820
1#
#830
0#
#840
b10110 ,
#850
1#
#860
0#
#870
b10111 ,
#880
1#
#890
0#
#900
b11000 ,
#910
1#
#920
0#
#930
b11001 ,
#940
1#
#950
0#
#960
b11010 ,
#970
1#
#980
0#
#990
b11011 ,
#1000
1#
#1010
0#
#1020
b11100 ,
#1030
1#
#1040
0#
#1050
b11101 ,
#1060
1#
#1070
0#
#1080
b11110 ,
#1090
1#
#1100
0#
#1110
b11111 ,
#1120
1#
#1130
0#
#1140
b100000 ,
#1150
1#
#1160
0#
#1170
b100001 ,
#1180
1#
#1190
0#
#1200
b100010 ,
#1210
1#
#1220
0#
#1230
b100011 ,
#1240
1#
#1250
0#
#1260
b100100 ,
#1270
1#
#1280
0#
#1290
b100101 ,
#1300
1#
#1310
0#
#1320
b100110 ,
#1330
1#
#1340
0#
#1350
b100111 ,
#1360
1#
#1370
0#
#1380
b101000 ,
#1390
1#
#1400
0#
#1410
b101001 ,
#1420
1#
#1430
0#
#1440
b101010 ,
#1450
1#
#1460
0#
#1470
b101011 ,
#1480
1#
#1490
0#
#1500
b101100 ,
#1510
1#
#1520
0#
#1530
b101101 ,
#1540
1#
#1550
0#
#1560
b101110 ,
#1570
1#
#1580
0#
#1590
b101111 ,
#1600
1#
#1610
0#
#1620
b110000 ,
#1630
1#
#1640
0#
#1650
b110001 ,
#1660
1#
#1670
0#
#1680
b110010 ,
#1690
1#
#1700
0#
#1710
b110011 ,
#1720
1#
#1730
0#
#1740
b110100 ,
#1750
1#
#1760
0#
#1770
b110101 ,
#1780
1#
#1790
0#
#1800
b110110 ,
#1810
1#
#1820
0#
#1830
b110111 ,
#1840
1#
#1850
0#
#1860
b111000 ,
#1870
1#
#1880
0#
#1890
b111001 ,
#1900
1#
#1910
0#
#1920
b111010 ,
#1930
1#
#1940
0#
#1950
b111011 ,
#1960
1#
#1970
0#
#1980
b111100 ,
#1990
1#
#2000
0#
#2010
b111101 ,
#2020
1#
#2030
0#
#2040
b111110 ,
#2050
1#
#2060
0#
#2070
b111111 ,
#2080
1#
#2090
0#
#2100
b1000000 ,
#2110
1#
#2120
0#
#2130
b1000001 ,
#2140
1#
#2150
0#
#2160
b1000010 ,
#2170
1#
#2180
0#
#2190
b1000011 ,
#2200
1#
#2210
0#
#2220
b1000100 ,
#2230
1#
#2240
0#
#2250
b1000101 ,
#2260
1#
#2270
0#
#2280
b1000110 ,
#2290
1#
#2300
0#
#2310
b1000111 ,
#2320
1#
#2330
0#
#2340
b1001000 ,
#2350
1#
#2360
0#
#2370
b1001001 ,
#2380
1#
#2390
0#
#2400
b1001010 ,
#2410
1#
#2420
0#
#2430
b1001011 ,
#2440
1#
#2450
0#
#2460
b1001100 ,
#2470
1#
#2480
0#
#2490
b1001101 ,
#2500
1#
#2510
0#
#2520
b1001110 ,
#2530
1#
#2540
0#
#2550
b1001111 ,
#2560
1#
#2570
0#
#2580
b1010000 ,
#2590
1#
#2600
0#
#2610
b1010001 ,
#2620
1#
#2630
0#
#2640
b1010010 ,
#2650
1#
#2660
0#
#2670
b1010011 ,
#2680
1#
#2690
0#
#2700
b1010100 ,
#2710
1#
#2720
0#
#2730
b1010101 ,
#2740
1#
#2750
0#
#2760
b1010110 ,
#2770
1#
#2780
0#
#2790
b1010111 ,
#2800
1#
#2810
0#
#2820
b1011000 ,
#2830
1#
#2840
0#
#2850
b1011001 ,
#2860
1#
#2870
0#
#2880
b1011010 ,
#2890
1#
#2900
0#
#2910
b1011011 ,
#2920
1#
#2930
0#
#2940
b1011100 ,
#2950
1#
#2960
0#
#2970
b1011101 ,
#2980
1#
#2990
0#
#3000
b1011110 ,
#3010
1#
#3020
0#
#3030
b1011111 ,
#3040
1#
#3050
0#
#3060
b1100000 ,
#3070
1#
#3080
0#
#3090
b1100001 ,
#3100
1#
#3110
0#
#3120
b1100010 ,
#3130
1#
#3140
0#
#3150
b1100011 ,
#3160
1#
#3170
0#
#3180
b1100100 ,
#3190
b0 '
b0 /
b0 S
#3210
b1100 %
b1100 -
b1100 Q
#3230
1)
#3250
1#
#3260
0#
#3280
0)
#3300
b1 M
1*
#3320
b10 M
x7
xA
xC
18
1B
1D
b1 O
1#
#3330
0#
#3350
b10 M
0*
#3360
b0 ,
#3370
b0 !
b0 <
b0 V
b100 M
x3
14
0C
0D
0A
0B
07
08
b0 2
b0 ^
b0 >
b0 G
b0 \
b11000000000 @
b11000000000 Z
b10 O
1#
#3380
0#
#3390
b1 ,
#3400
b110 M
x3
14
b100 O
1#
#3410
0#
#3420
b10 ,
#3430
b1000 M
x3
14
b110 O
1#
#3440
0#
#3450
b11 ,
#3460
b1010 M
x3
14
b1000 O
1#
#3470
0#
#3480
b100 ,
#3490
b1100 M
x3
14
b1010 O
1#
#3500
0#
#3510
b101 ,
#3520
b1110 M
x3
14
b1100 O
1#
#3530
0#
#3540
b110 ,
#3550
b10000 M
x3
14
b1110 O
1#
#3560
0#
#3570
b111 ,
#3580
b0 M
1;
x3
14
b10000 O
1#
#3590
0#
#3600
b1000 ,
#3610
0;
03
04
b0 O
1#
#3620
0#
#3630
b1001 ,
#3640
1#
#3650
0#
#3660
b1010 ,
#3670
b1 '
b1 /
b1 S
#3690
b10 %
b10 -
b10 Q
#3710
1)
#3730
1#
#3740
0#
#3760
0)
#3780
b1 M
1*
#3800
b10 M
x7
xA
xC
18
1B
1D
b1 O
1#
#3810
0#
#3830
b10 M
0*
#3840
b0 ,
#3850
b11 M
x3
14
0C
0D
0A
0B
07
08
b1 >
b1 G
b1 \
b100000000 @
b100000000 Z
b10 O
1#
#3860
0#
#3870
b1 ,
#3880
b100 M
x5
16
03
04
b11 O
1#
#3890
0#
#3900
b10 ,
#3910
b100000000 !
b100000000 <
b100000000 V
b110 M
x3
14
05
06
b100000000 2
b100000000 ^
b100 O
b0 X
b1110 `
1#
#3920
0#
#3930
b11 ,
#3940
b1000 M
x3
14
b10000000 !
b10000000 <
b10000000 V
b110 O
b10000000 2
b10000000 ^
1#
#3950
0#
#3960
b100 ,
#3970
b1000000 !
b1000000 <
b1000000 V
b1010 M
x3
14
b1000000 2
b1000000 ^
b1000 O
1#
#3980
0#
#3990
b101 ,
#4000
b1100 M
x3
14
b100000 !
b100000 <
b100000 V
b1010 O
b100000 2
b100000 ^
1#
#4010
0#
#4020
b110 ,
#4030
b10000 !
b10000 <
b10000 V
b1110 M
x3
14
b10000 2
b10000 ^
b1100 O
1#
#4040
0#
#4050
b111 ,
#4060
b10000 M
x3
14
b1000 !
b1000 <
b1000 V
b1110 O
b1000 2
b1000 ^
1#
#4070
0#
#4080
b1000 ,
#4090
b100 !
b100 <
b100 V
b0 M
1;
x3
14
b100 2
b100 ^
b10000 O
1#
#4100
0#
#4110
b1001 ,
#4120
0;
03
04
b10 !
b10 <
b10 V
b0 O
b10 2
b10 ^
1#
#4130
0#
#4140
b1010 ,
#4150
1#
#4160
0#
#4170
b1011 ,
#4180
1#
#4190
0#
#4200
b1100 ,
#4210
1#
#4220
0#
#4230
b1101 ,
#4240
1#
#4250
0#
#4260
b1110 ,
#4270
1#
#4280
0#
#4290
b1111 ,
#4300
1#
#4310
0#
#4320
b10000 ,
#4330
1#
#4340
0#
#4350
b10001 ,
#4360
1#
#4370
0#
#4380
b10010 ,
#4390
1#
#4400
0#
#4410
b10011 ,
#4420
1#
#4430
0#
#4440
b10100 ,
#4450
1#
#4460
0#
#4470
b10101 ,
#4480
1#
#4490
0#
#4500
b10110 ,
#4510
1#
#4520
0#
#4530
b10111 ,
#4540
1#
#4550
0#
#4560
b11000 ,
#4570
1#
#4580
0#
#4590
b11001 ,
#4600
1#
#4610
0#
#4620
b11010 ,
#4630
1#
#4640
0#
#4650
b11011 ,
#4660
1#
#4670
0#
#4680
b11100 ,
#4690
1#
#4700
0#
#4710
b11101 ,
#4720
1#
#4730
0#
#4740
b11110 ,
#4750
1#
#4760
0#
#4770
b11111 ,
#4780
1#
#4790
0#
#4800
b100000 ,
#4810
1#
#4820
0#
#4830
b100001 ,
#4840
1#
#4850
0#
#4860
b100010 ,
#4870
1#
#4880
0#
#4890
b100011 ,
#4900
1#
#4910
0#
#4920
b100100 ,
#4930
1#
#4940
0#
#4950
b100101 ,
#4960
1#
#4970
0#
#4980
b100110 ,
#4990
1#
#5000
0#
#5010
b100111 ,
#5020
1#
#5030
0#
#5040
b101000 ,
#5050
1#
#5060
0#
#5070
b101001 ,
#5080
1#
#5090
0#
#5100
b101010 ,
#5110
1#
#5120
0#
#5130
b101011 ,
#5140
1#
#5150
0#
#5160
b101100 ,
#5170
1#
#5180
0#
#5190
b101101 ,
#5200
1#
#5210
0#
#5220
b101110 ,
#5230
1#
#5240
0#
#5250
b101111 ,
#5260
1#
#5270
0#
#5280
b110000 ,
#5290
1#
#5300
0#
#5310
b110001 ,
#5320
1#
#5330
0#
#5340
b110010 ,
#5350
1#
#5360
0#
#5370
b110011 ,
#5380
1#
#5390
0#
#5400
b110100 ,
#5410
1#
#5420
0#
#5430
b110101 ,
#5440
1#
#5450
0#
#5460
b110110 ,
#5470
1#
#5480
0#
#5490
b110111 ,
#5500
1#
#5510
0#
#5520
b111000 ,
#5530
1#
#5540
0#
#5550
b111001 ,
#5560
1#
#5570
0#
#5580
b111010 ,
#5590
1#
#5600
0#
#5610
b111011 ,
#5620
1#
#5630
0#
#5640
b111100 ,
#5650
1#
#5660
0#
#5670
b111101 ,
#5680
1#
#5690
0#
#5700
b111110 ,
#5710
1#
#5720
0#
#5730
b111111 ,
#5740
1#
#5750
0#
#5760
b1000000 ,
#5770
1#
#5780
0#
#5790
b1000001 ,
#5800
1#
#5810
0#
#5820
b1000010 ,
#5830
1#
#5840
0#
#5850
b1000011 ,
#5860
1#
#5870
0#
#5880
b1000100 ,
#5890
1#
#5900
0#
#5910
b1000101 ,
#5920
1#
#5930
0#
#5940
b1000110 ,
#5950
1#
#5960
0#
#5970
b1000111 ,
#5980
1#
#5990
0#
#6000
b1001000 ,
#6010
1#
#6020
0#
#6030
b1001001 ,
#6040
1#
#6050
0#
