Constant_Time_Multiplier/MultiplierControl_StateBranch.v
 //==============================================================================
// Control Module for Sequential Multiplier
//==============================================================================

module MultiplierControl_StateBranch #(parameter WIDTH = 4)(
	// External Inputs
	input   clk,           // Clock
    input   rst,           // reset
	input   start,

    // External Output
    output reg productDone,

	// Outputs to Datapath
	output reg  rsload,
	output reg  rsclear,
	output reg  rsshr,
    output reg  mrld,
    output reg  mdld,

	// Inputs from Datapath
    input [WIDTH - 1:0] multiplierReg
);
	// Local Vars
	// # of states = 2 * WIDTH + 3
    localparam STATE_WIDTH = $clog2(2 * WIDTH + 3);
    reg [STATE_WIDTH - 1:0] state;
	reg [STATE_WIDTH - 1:0] next_state;

	localparam START = 4'd0;
	localparam INIT = 4'd1;
    localparam FINAL = 2 * (WIDTH + 1) + WIDTH;
    // BIT_n = 2*n, BIT_n_TRUE = 2*n + 1, FINAL = 2*(N+1) + N

	// Output Combinational Logic
	always @( * ) begin
		// Set defaults
        rsload = 0;
        rsclear = 0;
        rsshr = 0;
        mrld = 0;
        mdld = 0;
        productDone = 0;
        if (state == START) begin
        end
        else if (state == INIT) begin
            mdld = 1;
            mrld = 1;
            rsclear = 1;
        end
        else if (state == FINAL) begin
            rsshr = 1;
            productDone = 1;
        end
        else if (state >= (WIDTH + 1) * 2) begin
            rsshr = 1;
        end
        else if (state[0] == 1) begin
            rsload = 1;
        end
	end

	// Next State Combinational Logic
	always @( * ) begin
		next_state = state;
		
		if (state == START) begin
			if (start) begin
				next_state = INIT;
			end
		end
		else if (state == INIT) begin
            next_state = (WIDTH + 1) * 2;
		end
        else if (state == FINAL) begin
            next_state = START;
        end
        else if (state >= (WIDTH + 1) * 2) begin
            if (multiplierReg[state - (WIDTH + 1) * 2]) begin
                next_state = (state - (WIDTH + 1) * 2) * 2 + 3;
            end
            else begin
                next_state = (state - (WIDTH + 1) * 2) * 2 + 2;
            end
        end
        else if (state[0] == 0) begin
            next_state = (next_state / 2) + (WIDTH + 1) * 2;
        end
        else begin
            next_state = ((next_state - 1) / 2) + (WIDTH + 1) * 2;
        end
	end

	// State Update Sequential Logic
	always @(posedge clk) begin
		if (rst) begin
			state <= START;
		end
		else begin
			// Update state to next state
			state <= next_state;
		end
	end

endmodule

MultiplierDatapath.v
//==============================================================================
// Datapath Module for Sequential Multiplier
//==============================================================================

module MultiplierDatapath #(parameter WIDTH = 4)(

    // External Inputs
    input   clk,       // Clock 
    input wire [WIDTH - 1:0] multiplier,
    input wire [WIDTH - 1:0] multiplicand,

    // External Output
    output wire [WIDTH*2 - 1:0] product,

    // Inputs from Controller
    input rsload,
    input rsclear,
    input rsshr,
    input mrld,
    input mdld,

    // Outputs to Controller
    output reg [WIDTH - 1:0] multiplierReg,

    // debug outputs
    output reg [WIDTH*2:0] runningSumReg,
    output reg [WIDTH*2:0] multiplicandReg
);

// Sequential Logic
always @( posedge clk) begin
    
    // init registers
    if (mdld) begin
        multiplicandReg <= multiplicand << WIDTH;
    end
    if (mrld) begin
        multiplierReg <= multiplier;
    end
    if (rsclear) begin
        runningSumReg <= 0;
    end

    // load running sum
    if (rsload) begin
        runningSumReg <= multiplicandReg + runningSumReg; 
    end
    // how do we know what to shift in here for sign?
    if(rsshr) begin
        runningSumReg <= runningSumReg >>> 1; 
    end
end 
    assign product = runningSumReg;

endmodule

Constant_Time_Multiplier/Multiplier_StateBranch.v
//==============================================================================
// Multiplier Module (runs in constant time for all inputs)
//==============================================================================

`include "MultiplierControl_StateBranch.v"
`include "../MultiplierDatapath.v"

module Multiplier_StateBranch #(parameter WIDTH = 2048)(
	input   clk,
	input   rst,
    input   start,
    input [WIDTH - 1:0] multiplier,
    input [WIDTH - 1:0] multiplicand,

	output [2*WIDTH - 1:0] product,
    output productDone
);
	// Declare local connections here
	wire rsload;
	wire rsclear;
	wire rsshr;
	wire mrld;
	wire mdld;
    wire mr0;
    wire mr1;
    wire mr2;
    wire mr3;
    wire [WIDTH - 1:0] multiplierReg;
    wire [WIDTH * 2:0] runningSumReg;
    wire [WIDTH * 2:0] multiplicandReg;

	// Datapath -- check port connections/rename
	MultiplierDatapath #(WIDTH) dpath(
		.clk    (clk),
        .multiplier (multiplier),
        .multiplicand (multiplicand),
        .rsload (rsload),
        .rsclear (rsclear),
        .rsshr (rsshr),
        .mrld (mrld),
        .mdld (mdld),
        .product (product),
        .multiplierReg(multiplierReg),
        .runningSumReg(runningSumReg),
        .multiplicandReg(multiplicandReg)
	);

	// Control
	MultiplierControl_StateBranch #(WIDTH) ctrl(
		.clk  (clk),
		.rst  (rst),
        .start (start),
        .rsload (rsload),
        .rsclear (rsclear),
        .rsshr (rsshr),
        .mrld (mrld),
        .mdld (mdld),
        .multiplierReg(multiplierReg),
        .productDone (productDone)
	);

endmodule

Constant_Time_Multiplier/Multiplier_StateBranch.t.v
//===============================================================================
// Testbench Module for Constant Time Multiplier
// some code adapted from ECE206 testing material
//===============================================================================
`timescale 1ns/100ps

`include "Multiplier_StateBranch.v"

`define ASSERT_EQ(ONE, TWO, MSG)               \
	begin                                      \
		if ((ONE) !== (TWO)) begin             \
			$display("\t[FAILURE]:%s", (MSG)); \
			errors = errors + 1;               \
		end                                    \
	end #0

`define SET(VAR, VALUE) $display("Setting %s to %s...", "VAR", "VALUE"); #1; VAR = (VALUE); #1

`define CLOCK $display("Pressing uclk..."); #1; clk = 1; #1; clk = 0; #1

`define SHOW_STATE(STATE) $display("\nEntering State: %s\n-----------------------------------", STATE)

module MultiplierTest;
    parameter NUM_BITS = 7;

	// Local Vars
	reg clk = 0;
	reg rst = 0;
	reg start = 0;
	reg [NUM_BITS - 1:0] multiplier = 7'd0;
	reg [NUM_BITS - 1:0] multiplicand = 7'd0;
    wire [2 * NUM_BITS - 1:0] product;

	// Error Counts
	reg [7:0] errors = 0;

	// VCD Dump
	initial begin
		$dumpfile("MultiplierTest.vcd");
		$dumpvars;
	end

	// Multiplier Module
	Multiplier_StateBranch #(NUM_BITS) multipliertester(
        .clk    (clk),
		.rst    (rst),
        .start  (start),
        .multiplier (multiplier),
        .multiplicand (multiplicand),
        .product (product)
	);

    integer i;
	// Main Test Logic
	initial begin
        // 0110 x 0011
        /*
        `SET(multiplier, 4'b0011)
        `SET(multiplicand, 4'b0110)

		// Reset the multiplier
		`SET(rst, 1);
		`CLOCK;

		// START State
		`SET(rst, 0);
        `SET(start, 1);
        `CLOCK;

        // INIT State - should take at most 10 clock cycles to get back to START
        `SET(start, 0);
        for (i = 0; i < 10; i = i + 1) begin
            `CLOCK;
        end
        `ASSERT_EQ(product, 8'b00010010, "Product is incorrect");
        */

        // 15 x 15
        `SET(multiplier, 15)
        `SET(multiplicand, 15)

		`SET(rst, 1);
		`CLOCK;

		`SET(rst, 0);
        `SET(start, 1);
        `CLOCK;

        `SET(start, 0);

        for (i = 0; i < 100; i = i + 1) begin
            `CLOCK;
        end
        `ASSERT_EQ(product, 225, "Product is incorrect");
        $display("%b", product);

        // 0 x 12
        `SET(multiplier, 0)
        `SET(multiplicand, 12)

		`SET(rst, 1);
		`CLOCK;

		`SET(rst, 0);
        `SET(start, 1);
        `CLOCK;

        `SET(start, 0);

        for (i = 0; i < 10; i = i + 1) begin
            `CLOCK;
        end
        `ASSERT_EQ(product, 0, "Product is incorrect");

        // 1 x 2
        `SET(multiplier, 1)
        `SET(multiplicand, 2)

		`SET(rst, 1);
		`CLOCK;

		`SET(rst, 0);
        `SET(start, 1);
        `CLOCK;

        `SET(start, 0);

        for (i = 0; i < 100; i = i + 1) begin
            `CLOCK;
        end
        `ASSERT_EQ(product, 2, "Product is incorrect");

        // 0 x 0 
        `SET(multiplier, 0)
        `SET(multiplicand, 0)

		`SET(rst, 1);
		`CLOCK;

		`SET(rst, 0);
        `SET(start, 1);
        `CLOCK;

        `SET(start, 0);

        for (i = 0; i < 100; i = i + 1) begin
            `CLOCK;
        end
        `ASSERT_EQ(product, 0, "Product is incorrect");

        // 92 * 75
        `SET(multiplier, 92)
        `SET(multiplicand, 75)

		`SET(rst, 1);
		`CLOCK;

		`SET(rst, 0);
        `SET(start, 1);
        `CLOCK;

        `SET(start, 0);

        for (i = 0; i < 100; i = i + 1) begin
            `CLOCK;
        end
        `ASSERT_EQ(product, 6900, "Product is incorrect");

        // 42 * 78
        `SET(multiplier, 92)
        `SET(multiplicand, 75)

		`SET(rst, 1);
		`CLOCK;

		`SET(rst, 0);
        `SET(start, 1);
        `CLOCK;

        `SET(start, 0);

        for (i = 0; i < 100; i = i + 1) begin
            `CLOCK;
        end
        `ASSERT_EQ(product, 3276, "Product is incorrect");


		$display("\nTESTS COMPLETED (%d FAILURES)", errors);
		$finish;
	end

endmodule

Constant_Time_Multiplier/MultiplierTest.vcd
$date
	Mon Jul  1 15:12:23 2024
$end
$version
	Icarus Verilog
$end
$timescale
	100ps
$end
$scope module MultiplierTest $end
$var wire 14 ! product [13:0] $end
$var parameter 32 " NUM_BITS $end
$var reg 1 # clk $end
$var reg 8 $ errors [7:0] $end
$var reg 7 % multiplicand [6:0] $end
$var reg 7 & multiplier [6:0] $end
$var reg 1 ' rst $end
$var reg 1 ( start $end
$var integer 32 ) i [31:0] $end
$scope module multipliertester $end
$var wire 1 # clk $end
$var wire 7 * multiplicand [6:0] $end
$var wire 7 + multiplier [6:0] $end
$var wire 1 ' rst $end
$var wire 1 ( start $end
$var wire 15 , runningSumReg [14:0] $end
$var wire 1 - rsshr $end
$var wire 1 . rsload $end
$var wire 1 / rsclear $end
$var wire 1 0 productDone $end
$var wire 14 1 product [13:0] $end
$var wire 7 2 multiplierReg [6:0] $end
$var wire 15 3 multiplicandReg [14:0] $end
$var wire 1 4 mrld $end
$var wire 1 5 mdld $end
$var parameter 32 6 WIDTH $end
$scope module ctrl $end
$var wire 1 # clk $end
$var wire 1 ' rst $end
$var wire 1 ( start $end
$var wire 7 7 multiplierReg [6:0] $end
$var parameter 65 8 FINAL $end
$var parameter 4 9 INIT $end
$var parameter 4 : START $end
$var parameter 32 ; STATE_WIDTH $end
$var parameter 32 < WIDTH $end
$var reg 1 5 mdld $end
$var reg 1 4 mrld $end
$var reg 5 = next_state [4:0] $end
$var reg 1 0 productDone $end
$var reg 1 / rsclear $end
$var reg 1 . rsload $end
$var reg 1 - rsshr $end
$var reg 5 > state [4:0] $end
$upscope $end
$scope module dpath $end
$var wire 1 # clk $end
$var wire 1 5 mdld $end
$var wire 1 4 mrld $end
$var wire 7 ? multiplicand [6:0] $end
$var wire 7 @ multiplier [6:0] $end
$var wire 1 / rsclear $end
$var wire 1 . rsload $end
$var wire 1 - rsshr $end
$var wire 14 A product [13:0] $end
$var parameter 32 B WIDTH $end
$var reg 15 C multiplicandReg [14:0] $end
$var reg 7 D multiplierReg [6:0] $end
$var reg 15 E runningSumReg [14:0] $end
$upscope $end
$upscope $end
$upscope $end
$enddefinitions $end
$comment Show the parameter values. $end
$dumpall
b111 B
b111 <
b101 ;
b0 :
b1 9
b10111 8
b111 6
b111 "
$end
#0
$dumpvars
bx E
bx D
bx C
bx A
b0 @
b0 ?
bx >
bx =
bx 7
x5
x4
bx 3
bx 2
bx 1
x0
x/
x.
x-
bx ,
b0 +
b0 *
bx )
0(
0'
b0 &
b0 %
b0 $
0#
bx !
$end
#10
b1111 &
b1111 +
b1111 @
#30
b1111 %
b1111 *
b1111 ?
#50
1'
#70
b0 =
00
05
04
0-
0/
0.
b0 >
1#
#80
0#
#100
0'
#120
b1 =
1(
#140
b10000 =
1/
14
15
b1 >
1#
#150
0#
#170
b10000 =
0(
#180
b0 )
#190
b0 !
b0 1
b0 A
b11 =
1-
05
04
0/
b0 ,
b0 E
b1111 2
b1111 7
b1111 D
b11110000000 3
b11110000000 C
b10000 >
1#
#200
0#
#210
b1 )
#220
b10001 =
1.
0-
b11 >
1#
#230
0#
#240
b10 )
#250
b11110000000 !
b11110000000 1
b11110000000 A
b101 =
1-
0.
b11110000000 ,
b11110000000 E
b10001 >
1#
#260
0#
#270
b11 )
#280
b10010 =
1.
0-
b1111000000 !
b1111000000 1
b1111000000 A
b101 >
b1111000000 ,
b1111000000 E
1#
#290
0#
#300
b100 )
#310
b101101000000 !
b101101000000 1
b101101000000 A
b111 =
1-
0.
b101101000000 ,
b101101000000 E
b10010 >
1#
#320
0#
#330
b101 )
#340
b10011 =
1.
0-
b10110100000 !
b10110100000 1
b10110100000 A
b111 >
b10110100000 ,
b10110100000 E
1#
#350
0#
#360
b110 )
#370
b110100100000 !
b110100100000 1
b110100100000 A
b1001 =
1-
0.
b110100100000 ,
b110100100000 E
b10011 >
1#
#380
0#
#390
b111 )
#400
b10100 =
1.
0-
b11010010000 !
b11010010000 1
b11010010000 A
b1001 >
b11010010000 ,
b11010010000 E
1#
#410
0#
#420
b1000 )
#430
b111000010000 !
b111000010000 1
b111000010000 A
b1010 =
1-
0.
b111000010000 ,
b111000010000 E
b10100 >
1#
#440
0#
#450
b1001 )
#460
b10101 =
0-
b11100001000 !
b11100001000 1
b11100001000 A
b1010 >
b11100001000 ,
b11100001000 E
1#
#470
0#
#480
b1010 )
#490
b1100 =
1-
b10101 >
1#
#500
0#
#510
b1011 )
#520
b10110 =
0-
b1110000100 !
b1110000100 1
b1110000100 A
b1100 >
b1110000100 ,
b1110000100 E
1#
#530
0#
#540
b1100 )
#550
b1110 =
1-
b10110 >
1#
#560
0#
#570
b1101 )
#580
b10111 =
0-
b111000010 !
b111000010 1
b111000010 A
b1110 >
b111000010 ,
b111000010 E
1#
#590
0#
#600
b1110 )
#610
b0 =
10
1-
b10111 >
1#
#620
0#
#630
b1111 )
#640
00
0-
b11100001 !
b11100001 1
b11100001 A
b0 >
b11100001 ,
b11100001 E
1#
#650
0#
#660
b10000 )
#670
1#
#680
0#
#690
b10001 )
#700
1#
#710
0#
#720
b10010 )
#730
1#
#740
0#
#750
b10011 )
#760
1#
#770
0#
#780
b10100 )
#790
1#
#800
0#
#810
b10101 )
#820
1#
#830
0#
#840
b10110 )
#850
1#
#860
0#
#870
b10111 )
#880
1#
#890
0#
#900
b11000 )
#910
1#
#920
0#
#930
b11001 )
#940
1#
#950
0#
#960
b11010 )
#970
1#
#980
0#
#990
b11011 )
#1000
1#
#1010
0#
#1020
b11100 )
#1030
1#
#1040
0#
#1050
b11101 )
#1060
1#
#1070
0#
#1080
b11110 )
#1090
1#
#1100
0#
#1110
b11111 )
#1120
1#
#1130
0#
#1140
b100000 )
#1150
1#
#1160
0#
#1170
b100001 )
#1180
1#
#1190
0#
#1200
b100010 )
#1210
1#
#1220
0#
#1230
b100011 )
#1240
1#
#1250
0#
#1260
b100100 )
#1270
1#
#1280
0#
#1290
b100101 )
#1300
1#
#1310
0#
#1320
b100110 )
#1330
1#
#1340
0#
#1350
b100111 )
#1360
1#
#1370
0#
#1380
b101000 )
#1390
1#
#1400
0#
#1410
b101001 )
#1420
1#
#1430
0#
#1440
b101010 )
#1450
1#
#1460
0#
#1470
b101011 )
#1480
1#
#1490
0#
#1500
b101100 )
#1510
1#
#1520
0#
#1530
b101101 )
#1540
1#
#1550
0#
#1560
b101110 )
#1570
1#
#1580
0#
#1590
b101111 )
#1600
1#
#1610
0#
#1620
b110000 )
#1630
1#
#1640
0#
#1650
b110001 )
#1660
1#
#1670
0#
#1680
b110010 )
#1690
1#
#1700
0#
#1710
b110011 )
#1720
1#
#1730
0#
#1740
b110100 )
#1750
1#
#1760
0#
#1770
b110101 )
#1780
1#
#1790
0#
#1800
b110110 )
#1810
1#
#1820
0#
#1830
b110111 )
#1840
1#
#1850
0#
#1860
b111000 )
#1870
1#
#1880
0#
#1890
b111001 )
#1900
1#
#1910
0#
#1920
b111010 )
#1930
1#
#1940
0#
#1950
b111011 )
#1960
1#
#1970
0#
#1980
b111100 )
#1990
1#
#2000
0#
#2010
b111101 )
#2020
1#
#2030
0#
#2040
b111110 )
#2050
1#
#2060
0#
#2070
b111111 )
#2080
1#
#2090
0#
#2100
b1000000 )
#2110
1#
#2120
0#
#2130
b1000001 )
#2140
1#
#2150
0#
#2160
b1000010 )
#2170
1#
#2180
0#
#2190
b1000011 )
#2200
1#
#2210
0#
#2220
b1000100 )
#2230
1#
#2240
0#
#2250
b1000101 )
#2260
1#
#2270
0#
#2280
b1000110 )
#2290
1#
#2300
0#
#2310
b1000111 )
#2320
1#
#2330
0#
#2340
b1001000 )
#2350
1#
#2360
0#
#2370
b1001001 )
#2380
1#
#2390
0#
#2400
b1001010 )
#2410
1#
#2420
0#
#2430
b1001011 )
#2440
1#
#2450
0#
#2460
b1001100 )
#2470
1#
#2480
0#
#2490
b1001101 )
#2500
1#
#2510
0#
#2520
b1001110 )
#2530
1#
#2540
0#
#2550
b1001111 )
#2560
1#
#2570
0#
#2580
b1010000 )
#2590
1#
#2600
0#
#2610
b1010001 )
#2620
1#
#2630
0#
#2640
b1010010 )
#2650
1#
#2660
0#
#2670
b1010011 )
#2680
1#
#2690
0#
#2700
b1010100 )
#2710
1#
#2720
0#
#2730
b1010101 )
#2740
1#
#2750
0#
#2760
b1010110 )
#2770
1#
#2780
0#
#2790
b1010111 )
#2800
1#
#2810
0#
#2820
b1011000 )
#2830
1#
#2840
0#
#2850
b1011001 )
#2860
1#
#2870
0#
#2880
b1011010 )
#2890
1#
#2900
0#
#2910
b1011011 )
#2920
1#
#2930
0#
#2940
b1011100 )
#2950
1#
#2960
0#
#2970
b1011101 )
#2980
1#
#2990
0#
#3000
b1011110 )
#3010
1#
#3020
0#
#3030
b1011111 )
#3040
1#
#3050
0#
#3060
b1100000 )
#3070
1#
#3080
0#
#3090
b1100001 )
#3100
1#
#3110
0#
#3120
b1100010 )
#3130
1#
#3140
0#
#3150
b1100011 )
#3160
1#
#3170
0#
#3180
b1100100 )
#3190
b0 &
b0 +
b0 @
#3210
b1100 %
b1100 *
b1100 ?
#3230
1'
#3250
1#
#3260
0#
#3280
0'
#3300
b1 =
1(
#3320
b10000 =
1/
14
15
b1 >
1#
#3330
0#
#3350
b10000 =
0(
#3360
b0 )
#3370
b0 !
b0 1
b0 A
b10 =
1-
05
04
0/
b0 ,
b0 E
b0 2
b0 7
b0 D
b11000000000 3
b11000000000 C
b10000 >
1#
#3380
0#
#3390
b1 )
#3400
b10001 =
0-
b10 >
1#
#3410
0#
#3420
b10 )
#3430
b100 =
1-
b10001 >
1#
#3440
0#
#3450
b11 )
#3460
b10010 =
0-
b100 >
1#
#3470
0#
#3480
b100 )
#3490
b110 =
1-
b10010 >
1#
#3500
0#
#3510
b101 )
#3520
b10011 =
0-
b110 >
1#
#3530
0#
#3540
b110 )
#3550
b1000 =
1-
b10011 >
1#
#3560
0#
#3570
b111 )
#3580
b10100 =
0-
b1000 >
1#
#3590
0#
#3600
b1000 )
#3610
b1010 =
1-
b10100 >
1#
#3620
0#
#3630
b1001 )
#3640
b10101 =
0-
b1010 >
1#
#3650
0#
#3660
b1010 )
#3670
b1 &
b1 +
b1 @
#3690
b10 %
b10 *
b10 ?
#3710
1'
#3730
b0 =
b0 >
1#
#3740
0#
#3760
0'
#3780
b1 =
1(
#3800
b10000 =
1/
14
15
b1 >
1#
#3810
0#
#3830
b10000 =
0(
#3840
b0 )
#3850
b11 =
1-
05
04
0/
b1 2
b1 7
b1 D
b100000000 3
b100000000 C
b10000 >
1#
#3860
0#
#3870
b1 )
#3880
b10001 =
1.
0-
b11 >
1#
#3890
0#
#3900
b10 )
#3910
b100000000 !
b100000000 1
b100000000 A
b100 =
1-
0.
b100000000 ,
b100000000 E
b10001 >
1#
#3920
0#
#3930
b11 )
#3940
b10010 =
0-
b10000000 !
b10000000 1
b10000000 A
b100 >
b10000000 ,
b10000000 E
1#
#3950
0#
#3960
b100 )
#3970
b110 =
1-
b10010 >
1#
#3980
0#
#3990
b101 )
#4000
b10011 =
0-
b1000000 !
b1000000 1
b1000000 A
b110 >
b1000000 ,
b1000000 E
1#
#4010
0#
#4020
b110 )
#4030
b1000 =
1-
b10011 >
1#
#4040
0#
#4050
b111 )
#4060
b10100 =
0-
b100000 !
b100000 1
b100000 A
b1000 >
b100000 ,
b100000 E
1#
#4070
0#
#4080
b1000 )
#4090
b1010 =
1-
b10100 >
1#
#4100
0#
#4110
b1001 )
#4120
b10101 =
0-
b10000 !
b10000 1
b10000 A
b1010 >
b10000 ,
b10000 E
1#
#4130
0#
#4140
b1010 )
#4150
b1100 =
1-
b10101 >
1#
#4160
0#
#4170
b1011 )
#4180
b10110 =
0-
b1000 !
b1000 1
b1000 A
b1100 >
b1000 ,
b1000 E
1#
#4190
0#
#4200
b1100 )
#4210
b1110 =
1-
b10110 >
1#
#4220
0#
#4230
b1101 )
#4240
b10111 =
0-
b100 !
b100 1
b100 A
b1110 >
b100 ,
b100 E
1#
#4250
0#
#4260
b1110 )
#4270
b0 =
10
1-
b10111 >
1#
#4280
0#
#4290
b1111 )
#4300
00
0-
b10 !
b10 1
b10 A
b0 >
b10 ,
b10 E
1#
#4310
0#
#4320
b10000 )
#4330
1#
#4340
0#
#4350
b10001 )
#4360
1#
#4370
0#
#4380
b10010 )
#4390
1#
#4400
0#
#4410
b10011 )
#4420
1#
#4430
0#
#4440
b10100 )
#4450
1#
#4460
0#
#4470
b10101 )
#4480
1#
#4490
0#
#4500
b10110 )
#4510
1#
#4520
0#
#4530
b10111 )
#4540
1#
#4550
0#
#4560
b11000 )
#4570
1#
#4580
0#
#4590
b11001 )
#4600
1#
#4610
0#
#4620
b11010 )
#4630
1#
#4640
0#
#4650
b11011 )
#4660
1#
#4670
0#
#4680
b11100 )
#4690
1#
#4700
0#
#4710
b11101 )
#4720
1#
#4730
0#
#4740
b11110 )
#4750
1#
#4760
0#
#4770
b11111 )
#4780
1#
#4790
0#
#4800
b100000 )
#4810
1#
#4820
0#
#4830
b100001 )
#4840
1#
#4850
0#
#4860
b100010 )
#4870
1#
#4880
0#
#4890
b100011 )
#4900
1#
#4910
0#
#4920
b100100 )
#4930
1#
#4940
0#
#4950
b100101 )
#4960
1#
#4970
0#
#4980
b100110 )
#4990
1#
#5000
0#
#5010
b100111 )
#5020
1#
#5030
0#
#5040
b101000 )
#5050
1#
#5060
0#
#5070
b101001 )
#5080
1#
#5090
0#
#5100
b101010 )
#5110
1#
#5120
0#
#5130
b101011 )
#5140
1#
#5150
0#
#5160
b101100 )
#5170
1#
#5180
0#
#5190
b101101 )
#5200
1#
#5210
0#
#5220
b101110 )
#5230
1#
#5240
0#
#5250
b101111 )
#5260
1#
#5270
0#
#5280
b110000 )
#5290
1#
#5300
0#
#5310
b110001 )
#5320
1#
#5330
0#
#5340
b110010 )
#5350
1#
#5360
0#
#5370
b110011 )
#5380
1#
#5390
0#
#5400
b110100 )
#5410
1#
#5420
0#
#5430
b110101 )
#5440
1#
#5450
0#
#5460
b110110 )
#5470
1#
#5480
0#
#5490
b110111 )
#5500
1#
#5510
0#
#5520
b111000 )
#5530
1#
#5540
0#
#5550
b111001 )
#5560
1#
#5570
0#
#5580
b111010 )
#5590
1#
#5600
0#
#5610
b111011 )
#5620
1#
#5630
0#
#5640
b111100 )
#5650
1#
#5660
0#
#5670
b111101 )
#5680
1#
#5690
0#
#5700
b111110 )
#5710
1#
#5720
0#
#5730
b111111 )
#5740
1#
#5750
0#
#5760
b1000000 )
#5770
1#
#5780
0#
#5790
b1000001 )
#5800
1#
#5810
0#
#5820
b1000010 )
#5830
1#
#5840
0#
#5850
b1000011 )
#5860
1#
#5870
0#
#5880
b1000100 )
#5890
1#
#5900
0#
#5910
b1000101 )
#5920
1#
#5930
0#
#5940
b1000110 )
#5950
1#
#5960
0#
#5970
b1000111 )
#5980
1#
#5990
0#
#6000
b1001000 )
#6010
1#
#6020
0#
#6030
b1001001 )
#6040
1#
#6050
0#
#6060
b1001010 )
#6070
1#
#6080
0#
#6090
b1001011 )
#6100
1#
#6110
0#
#6120
b1001100 )
#6130
1#
#6140
0#
#6150
b1001101 )
#6160
1#
#6170
0#
#6180
b1001110 )
#6190
1#
#6200
0#
#6210
b1001111 )
#6220
1#
#6230
0#
#6240
b1010000 )
#6250
1#
#6260
0#
#6270
b1010001 )
#6280
1#
#6290
0#
#6300
b1010010 )
#6310
1#
#6320
0#
#6330
b1010011 )
#6340
1#
#6350
0#
#6360
b1010100 )
#6370
1#
#6380
0#
#6390
b1010101 )
#6400
1#
#6410
0#
#6420
b1010110 )
#6430
1#
#6440
0#
#6450
b1010111 )
#6460
1#
#6470
0#
#6480
b1011000 )
#6490
1#
#6500
0#
#6510
b1011001 )
#6520
1#
#6530
0#
#6540
b1011010 )
#6550
1#
#6560
0#
#6570
b1011011 )
#6580
1#
#6590
0#
#6600
b1011100 )
#6610
1#
#6620
0#
#6630
b1011101 )
#6640
1#
#6650
0#
#6660
b1011110 )
#6670
1#
#6680
0#
#6690
b1011111 )
#6700
1#
#6710
0#
#6720
b1100000 )
#6730
1#
#6740
0#
#6750
b1100001 )
#6760
1#
#6770
0#
#6780
b1100010 )
#6790
1#
#6800
0#
#6810
b1100011 )
#6820
1#
#6830
0#
#6840
b1100100 )
#6850
b0 &
b0 +
b0 @
#6870
b0 %
b0 *
b0 ?
#6890
1'
#6910
1#
#6920
0#
#6940
0'
#6960
b1 =
1(
#6980
b10000 =
1/
14
15
b1 >
1#
#6990
0#
#7010
b10000 =
0(
#7020
b0 )
#7030
b0 !
b0 1
b0 A
b10 =
1-
05
04
0/
b0 ,
b0 E
b0 2
b0 7
b0 D
b0 3
b0 C
b10000 >
1#
#7040
0#
#7050
b1 )
#7060
b10001 =
0-
b10 >
1#
#7070
0#
#7080
b10 )
#7090
b100 =
1-
b10001 >
1#
#7100
0#
#7110
b11 )
#7120
b10010 =
0-
b100 >
1#
#7130
0#
#7140
b100 )
#7150
b110 =
1-
b10010 >
1#
#7160
0#
#7170
b101 )
#7180
b10011 =
0-
b110 >
1#
#7190
0#
#7200
b110 )
#7210
b1000 =
1-
b10011 >
1#
#7220
0#
#7230
b111 )
#7240
b10100 =
0-
b1000 >
1#
#7250
0#
#7260
b1000 )
#7270
b1010 =
1-
b10100 >
1#
#7280
0#
#7290
b1001 )
#7300
b10101 =
0-
b1010 >
1#
#7310
0#
#7320
b1010 )
#7330
b1100 =
1-
b10101 >
1#
#7340
0#
#7350
b1011 )
#7360
b10110 =
0-
b1100 >
1#
#7370
0#
#7380
b1100 )
#7390
b1110 =
1-
b10110 >
1#
#7400
0#
#7410
b1101 )
#7420
b10111 =
0-
b1110 >
1#
#7430
0#
#7440
b1110 )
#7450
b0 =
10
1-
b10111 >
1#
#7460
0#
#7470
b1111 )
#7480
00
0-
b0 >
1#
#7490
0#
#7500
b10000 )
#7510
1#
#7520
0#
#7530
b10001 )
#7540
1#
#7550
0#
#7560
b10010 )
#7570
1#
#7580
0#
#7590
b10011 )
#7600
1#
#7610
0#
#7620
b10100 )
#7630
1#
#7640
0#
#7650
b10101 )
#7660
1#
#7670
0#
#7680
b10110 )
#7690
1#
#7700
0#
#7710
b10111 )
#7720
1#
#7730
0#
#7740
b11000 )
#7750
1#
#7760
0#
#7770
b11001 )
#7780
1#
#7790
0#
#7800
b11010 )
#7810
1#
#7820
0#
#7830
b11011 )
#7840
1#
#7850
0#
#7860
b11100 )
#7870
1#
#7880
0#
#7890
b11101 )
#7900
1#
#7910
0#
#7920
b11110 )
#7930
1#
#7940
0#
#7950
b11111 )
#7960
1#
#7970
0#
#7980
b100000 )
#7990
1#
#8000
0#
#8010
b100001 )
#8020
1#
#8030
0#
#8040
b100010 )
#8050
1#
#8060
0#
#8070
b100011 )
#8080
1#
#8090
0#
#8100
b100100 )
#8110
1#
#8120
0#
#8130
b100101 )
#8140
1#
#8150
0#
#8160
b100110 )
#8170
1#
#8180
0#
#8190
b100111 )
#8200
1#
#8210
0#
#8220
b101000 )
#8230
1#
#8240
0#
#8250
b101001 )
#8260
1#
#8270
0#
#8280
b101010 )
#8290
1#
#8300
0#
#8310
b101011 )
#8320
1#
#8330
0#
#8340
b101100 )
#8350
1#
#8360
0#
#8370
b101101 )
#8380
1#
#8390
0#
#8400
b101110 )
#8410
1#
#8420
0#
#8430
b101111 )
#8440
1#
#8450
0#
#8460
b110000 )
#8470
1#
#8480
0#
#8490
b110001 )
#8500
1#
#8510
0#
#8520
b110010 )
#8530
1#
#8540
0#
#8550
b110011 )
#8560
1#
#8570
0#
#8580
b110100 )
#8590
1#
#8600
0#
#8610
b110101 )
#8620
1#
#8630
0#
#8640
b110110 )
#8650
1#
#8660
0#
#8670
b110111 )
#8680
1#
#8690
0#
#8700
b111000 )
#8710
1#
#8720
0#
#8730
b111001 )
#8740
1#
#8750
0#
#8760
b111010 )
#8770
1#
#8780
0#
#8790
b111011 )
#8800
1#
#8810
0#
#8820
b111100 )
#8830
1#
#8840
0#
#8850
b111101 )
#8860
1#
#8870
0#
#8880
b111110 )
#8890
1#
#8900
0#
#8910
b111111 )
#8920
1#
#8930
0#
#8940
b1000000 )
#8950
1#
#8960
0#
#8970
b1000001 )
#8980
1#
#8990
0#
#9000
b1000010 )
#9010
1#
#9020
0#
#9030
b1000011 )
#9040
1#
#9050
0#
#9060
b1000100 )
#9070
1#
#9080
0#
#9090
b1000101 )
#9100
1#
#9110
0#
#9120
b1000110 )
#9130
1#
#9140
0#
#9150
b1000111 )
#9160
1#
#9170
0#
#9180
b1001000 )
#9190
1#
#9200
0#
#9210
b1001001 )
#9220
1#
#9230
0#
#9240
b1001010 )
#9250
1#
#9260
0#
#9270
b1001011 )
#9280
1#
#9290
0#
#9300
b1001100 )
#9310
1#
#9320
0#
#9330
b1001101 )
#9340
1#
#9350
0#
#9360
b1001110 )
#9370
1#
#9380
0#
#9390
b1001111 )
#9400
1#
#9410
0#
#9420
b1010000 )
#9430
1#
#9440
0#
#9450
b1010001 )
#9460
1#
#9470
0#
